blumpkin
