Metadata-Version: 1.1
Name: blumpkin
Version: 0.4.2
Summary: Testing tooling
Home-page: https://github.com/balanced/blumpkin
Author: Balanced
Author-email: dev+blumpkin@balancedpayments.com
License: UNKNOWN
Platform: any
Classifier: Development Status :: 4 - Beta
Classifier: Intended Audience :: Developers
Classifier: Natural Language :: English
Classifier: License :: OSI Approved :: ISC License (ISCL)
Classifier: Programming Language :: Python
Classifier: Programming Language :: Python :: 2.7
